pdm_vscode/__init__.py
pdm_vscode/hook.py
pdm_vscode-0.1.0.dist-info/entry_points.txt
pdm_vscode-0.1.0.dist-info/WHEEL
pdm_vscode-0.1.0.dist-info/METADATA
pdm_vscode-0.1.0.dist-info/license_files/LICENSE
pdm_vscode-0.1.0.dist-info/RECORD
